{
  "zh": {
    "profile": "配置",
    "save": "保存",
    "delete": "删除",
    "language": "语言",
    "input_label": "输入 (文件/文件夹)",
    "browse": "浏览",
    "out_label": "输出目录",
    "format": "格式",
    "mode": "模式",
    "mode_export": "仅导出",
    "mode_render": "替换代码块",
    "mode_render_keep": "追加图片",
    "recursive": "递归",
    "path": "路径",
    "image_store": "图片存放",
    "per_file": "每文档 [name]_images (同目录)",
    "out_images": "单一 images (在输出目录)",
    "clear_log": "运行前清空日志",
    "backup": "修改前备份 .md",
    "render": "渲染",
    "dry_run": "试运行",
    "risk_title": "风险提示",
    "risk_msg": "输出目录与输入目录相同，且未开启备份，将覆盖源 Markdown。是否继续？",
    "delete_confirm": "删除配置 '{name}'?",
    "select_input": "选择输入",
    "select_folder": "选择文件夹",
    "select_files": "选择文件(可多选)",
    "files_suffix": "个文件",
    "profile_changed": "当前设置已修改，是否加载所选配置并覆盖当前更改？"
  },
  "en": {
    "profile": "Profile",
    "save": "Save",
    "delete": "Delete",
    "language": "Language",
    "input_label": "Input (File/Folder)",
    "browse": "Browse",
    "out_label": "Output Dir",
    "format": "Format",
    "mode": "Mode",
    "mode_export": "Export only",
    "mode_render": "Replace blocks",
    "mode_render_keep": "Keep + append",
    "recursive": "Recursive",
    "path": "Path",
    "image_store": "Image placement",
    "per_file": "Per file [name]_images (sibling)",
    "out_images": "Single images (under output)",
    "clear_log": "Clear log before run",
    "backup": "Backup .md before modify",
    "render": "Render",
    "dry_run": "Dry Run",
    "risk_title": "Risk Warning",
    "risk_msg": "Output equals input and backup is OFF. This will overwrite source Markdown. Continue?",
    "delete_confirm": "Delete profile '{name}'?",
    "select_input": "Select Input",
    "select_folder": "Select Folder",
    "select_files": "Select File(s)",
    "files_suffix": "files",
    "profile_changed": "Current settings changed. Load selected profile and discard changes?"
  }
}
